{
  "kind": "singleType",
  "collectionName": "home_banners",
  "info": {
    "singularName": "home-banner",
    "pluralName": "home-banners",
    "displayName": "HomeBanner",
    "description": ""
  },
  "options": {
    "draftAndPublish": true
  },
  "pluginOptions": {},
  "attributes": {
    "siteName1": {
      "type": "string",
      "required": true
    },
    "bonus1": {
      "type": "float",
      "required": true
    },
    "description1": {
      "type": "text",
      "required": true
    },
    "link1": {
      "type": "string"
    },
    "siteName2": {
      "type": "string",
      "required": true
    },
    "bonus2": {
      "type": "float",
      "required": true
    },
    "description2": {
      "type": "text",
      "required": true
    },
    "link2": {
      "type": "string",
      "required": true
    }
  }
}
